{"_type":"export","__export_format":4,"__export_date":"2023-05-25T19:43:03.792Z","__export_source":"insomnia.desktop.app:v2022.4.2","resources":[{"_id":"req_71deffed5de0455c9a70be388509ef5b","parentId":"fld_83921b17e29a4e7594f089d8de1fae3f","modified":1685043344394,"created":1685043344394,"url":"http://localhost:8080/authors","name":"Author - Register Author","description":"","method":"POST","body":{"mimeType":"application/json","text":"{\n\t\"firstName\":\"name1\",\n\t\"lastName\":\"lastName1\",\n\t\"birthdate\":\"10/10/1982\"\n}"},"parameters":[],"headers":[{"name":"Content-Type","value":"application/json","id":"pair_0a616721a98f495091ef93acaf5932cf"}],"authentication":{},"metaSortKey":-1679186963957,"isPrivate":false,"settingStoreCookies":true,"settingSendCookies":true,"settingDisableRenderRequestBody":false,"settingEncodeUrl":true,"settingRebuildPath":true,"settingFollowRedirects":"global","_type":"request"},{"_id":"fld_83921b17e29a4e7594f089d8de1fae3f","parentId":"wrk_9fd4297f038742bdba03f6bfdcd1ea26","modified":1685043344393,"created":1685043344393,"name":"Spring Boot CRUD Example","description":"","environment":{},"environmentPropertyOrder":null,"metaSortKey":-1000000000,"_type":"request_group"},{"_id":"wrk_9fd4297f038742bdba03f6bfdcd1ea26","parentId":null,"modified":1685043333113,"created":1685043333113,"name":"Spring Boot CRUD Example","description":"","scope":"collection","_type":"workspace"},{"_id":"req_a435c4d6f7a24bf8a288b667adb4ded7","parentId":"fld_83921b17e29a4e7594f089d8de1fae3f","modified":1685043344404,"created":1685043344404,"url":"http://localhost:8080/authors/1","name":"Author - Update Author","description":"","method":"PUT","body":{"mimeType":"application/json","text":"{\n\t\"firstName\":\"pepe\",\n\t\"lastName\":\"lastName1\",\n\t\"birthdate\":\"10/10/1981\"\n}"},"parameters":[],"headers":[{"name":"Content-Type","value":"application/json","id":"pair_0a616721a98f495091ef93acaf5932cf"}],"authentication":{},"metaSortKey":-1675256164016.5,"isPrivate":false,"settingStoreCookies":true,"settingSendCookies":true,"settingDisableRenderRequestBody":false,"settingEncodeUrl":true,"settingRebuildPath":true,"settingFollowRedirects":"global","_type":"request"},{"_id":"req_9ab0543e0f114420a75d2d58829e8c04","parentId":"fld_83921b17e29a4e7594f089d8de1fae3f","modified":1685043344396,"created":1685043344396,"url":"http://localhost:8080/authors/1","name":"Author - Find by Id","description":"","method":"GET","body":{},"parameters":[],"headers":[],"authentication":{},"metaSortKey":-1671325364076,"isPrivate":false,"settingStoreCookies":true,"settingSendCookies":true,"settingDisableRenderRequestBody":false,"settingEncodeUrl":true,"settingRebuildPath":true,"settingFollowRedirects":"global","_type":"request"},{"_id":"req_412caf53ca5742cfbcdbd42053bd7ebf","parentId":"fld_83921b17e29a4e7594f089d8de1fae3f","modified":1685043344400,"created":1685043344400,"url":"http://localhost:8080/authors/1","name":"Author - Delete By Id","description":"","method":"DELETE","body":{},"parameters":[],"headers":[],"authentication":{},"metaSortKey":-1671325362884.25,"isPrivate":false,"settingStoreCookies":true,"settingSendCookies":true,"settingDisableRenderRequestBody":false,"settingEncodeUrl":true,"settingRebuildPath":true,"settingFollowRedirects":"global","_type":"request"},{"_id":"req_7d081cd2a1134d28833e85f26eee6b4f","parentId":"fld_83921b17e29a4e7594f089d8de1fae3f","modified":1685043344398,"created":1685043344398,"url":"http://localhost:8080/authors/pages?q=lastName1&sortDirection=desc&page=5","name":"Author - Find All To Page","description":"","method":"GET","body":{},"parameters":[],"headers":[],"authentication":{},"metaSortKey":-1667394564135.5,"isPrivate":false,"settingStoreCookies":true,"settingSendCookies":true,"settingDisableRenderRequestBody":false,"settingEncodeUrl":true,"settingRebuildPath":true,"settingFollowRedirects":"global","_type":"request"},{"_id":"req_f06eb45c6f52472aaf663c4f23716807","parentId":"fld_83921b17e29a4e7594f089d8de1fae3f","modified":1685043344399,"created":1685043344399,"url":"http://localhost:8080/books","name":"Book - Register Book","description":"","method":"POST","body":{"mimeType":"application/json","text":"{\n\t\"title\":\"title 1\",\n\t\"publicationDate\":\"10/12/1988\",\n\t\"onlineAvailability\": true,\n\t\"authors\": [1,2,3]\n}"},"parameters":[],"headers":[{"name":"Content-Type","value":"application/json","id":"pair_0a616721a98f495091ef93acaf5932cf"}],"authentication":{},"metaSortKey":-1667394564085.5,"isPrivate":false,"settingStoreCookies":true,"settingSendCookies":true,"settingDisableRenderRequestBody":false,"settingEncodeUrl":true,"settingRebuildPath":true,"settingFollowRedirects":"global","_type":"request"},{"_id":"req_f3cfc1c24891423e87e8cde006b3117f","parentId":"fld_83921b17e29a4e7594f089d8de1fae3f","modified":1685043344405,"created":1685043344405,"url":"http://localhost:8080/books/1","name":"Book - Find by Id","description":"","method":"GET","body":{},"parameters":[],"headers":[],"authentication":{},"metaSortKey":-1667394564035.5,"isPrivate":false,"settingStoreCookies":true,"settingSendCookies":true,"settingDisableRenderRequestBody":false,"settingEncodeUrl":true,"settingRebuildPath":true,"settingFollowRedirects":"global","_type":"request"},{"_id":"req_d46cc68196d4436cb075c046e6eed249","parentId":"fld_83921b17e29a4e7594f089d8de1fae3f","modified":1685043344406,"created":1685043344406,"url":"http://localhost:8080/books/1","name":"Book - Delete By Id","description":"","method":"DELETE","body":{},"parameters":[],"headers":[],"authentication":{},"metaSortKey":-1667394563985.5,"isPrivate":false,"settingStoreCookies":true,"settingSendCookies":true,"settingDisableRenderRequestBody":false,"settingEncodeUrl":true,"settingRebuildPath":true,"settingFollowRedirects":"global","_type":"request"},{"_id":"req_c523fe6b8d1346b3bbe6a43325cbffe3","parentId":"fld_83921b17e29a4e7594f089d8de1fae3f","modified":1685043344408,"created":1685043344408,"url":"http://localhost:8080/books/pages?page=0&q=title","name":"Book - Find All To Page","description":"","method":"GET","body":{},"parameters":[],"headers":[],"authentication":{},"metaSortKey":-1667394563935.5,"isPrivate":false,"settingStoreCookies":true,"settingSendCookies":true,"settingDisableRenderRequestBody":false,"settingEncodeUrl":true,"settingRebuildPath":true,"settingFollowRedirects":"global","_type":"request"},{"_id":"env_389c53bbcfb868ba58249b16d0b13cf1cc7dfbe0","parentId":"wrk_9fd4297f038742bdba03f6bfdcd1ea26","modified":1685043333117,"created":1685043333117,"name":"Base Environment","data":{},"dataPropertyOrder":null,"color":null,"isPrivate":false,"metaSortKey":1685043333117,"_type":"environment"},{"_id":"jar_389c53bbcfb868ba58249b16d0b13cf1cc7dfbe0","parentId":"wrk_9fd4297f038742bdba03f6bfdcd1ea26","modified":1685043333118,"created":1685043333118,"name":"Default Jar","cookies":[],"_type":"cookie_jar"},{"_id":"spc_5e1f6c9a29ea4d19a6a40695146f957d","parentId":"wrk_9fd4297f038742bdba03f6bfdcd1ea26","modified":1685043333114,"created":1685043333114,"fileName":"Spring Boot CRUD Example","contents":"","contentType":"yaml","_type":"api_spec"}]}